{"operators":[{"globalTypeIndex":11,"caption":"RedButton","index":0,"posX":10,"posY":10,"configurationData":null},{"globalTypeIndex":9,"caption":"GreenButton","index":1,"posX":10,"posY":150,"configurationData":null},{"globalTypeIndex":1,"caption":"AND","index":2,"posX":250,"posY":10,"configurationData":null},{"globalTypeIndex":15,"caption":"RedLed","index":3,"posX":510,"posY":90,"configurationData":null}],"links":[{"color":"blue","fromOperatorIndex":0,"fromOutput":0,"toOperatorIndex":2,"toInput":0},{"color":"blue","fromOperatorIndex":1,"fromOutput":0,"toOperatorIndex":2,"toInput":1},{"color":"blue","fromOperatorIndex":2,"fromOutput":0,"toOperatorIndex":3,"toInput":0}]}